README.md
setup.py
self_driving_desktop/__init__.py
self_driving_desktop/__main__.py
self_driving_desktop/grammar.py
self_driving_desktop/keymap.py
self_driving_desktop/parser.py
self_driving_desktop/recorder.py
self_driving_desktop.egg-info/PKG-INFO
self_driving_desktop.egg-info/SOURCES.txt
self_driving_desktop.egg-info/dependency_links.txt
self_driving_desktop.egg-info/entry_points.txt
self_driving_desktop.egg-info/requires.txt
self_driving_desktop.egg-info/top_level.txt