Metadata-Version: 2.1
Name: self-driving-desktop
Version: 0.0.6
Summary: Desktop Automation Framework. Drive your keyboard and mouse with text files.
Home-page: https://github.com/hofstadter-io/self-driving-desktop
Author: Hofstadter, Inc.
Author-email: support@hofstadter.io
License: UNKNOWN
Keywords: desktop automation,automation,gui,mouse,keyboard,driver,recorder
Platform: UNKNOWN
